neuroglia/__init__.py
neuroglia/calcium.py
neuroglia/event.py
neuroglia/nwb.py
neuroglia/spike.py
neuroglia/tensor.py
neuroglia/trace.py
neuroglia/utils.py
neuroglia-0.1.0.dist-info/DESCRIPTION.rst
neuroglia-0.1.0.dist-info/METADATA
neuroglia-0.1.0.dist-info/RECORD
neuroglia-0.1.0.dist-info/WHEEL
neuroglia-0.1.0.dist-info/metadata.json
neuroglia-0.1.0.dist-info/top_level.txt
tests/__init__.py
tests/test_calcium.py
tests/test_event.py
tests/test_nwb.py
tests/test_spike.py
tests/test_tensor.py
tests/test_traces.py
tests/test_utils.py
