Metadata-Version: 2.0
Name: neuroglia
Version: 0.1.0
Summary: scikit-learn compatible transformers for neural data science
Home-page: https://github.com/AllenInstitute/neuroglia
Author: Justin Kiggins
Author-email: justink@alleninstitute.org
License: UNKNOWN
Platform: UNKNOWN
Classifier: Development Status :: 2 - Pre-Alpha
Classifier: Programming Language :: Python
Classifier: Programming Language :: Python :: 2
Classifier: Programming Language :: Python :: 2.7
Classifier: Programming Language :: Python :: 3
Classifier: Programming Language :: Python :: 3.5
Classifier: Programming Language :: Python :: 3.6
Requires-Dist: pandas
Requires-Dist: scikit-learn
Requires-Dist: xarray
